kq_lmpc_quadrotor/QuadrotorKoopman.py
kq_lmpc_quadrotor/__init__.py
quadrotor_koopman_datafree-1.0.dist-info/licenses/LICENSE
quadrotor_koopman_datafree-1.0.dist-info/METADATA
quadrotor_koopman_datafree-1.0.dist-info/WHEEL
quadrotor_koopman_datafree-1.0.dist-info/entry_points.txt
quadrotor_koopman_datafree-1.0.dist-info/top_level.txt
quadrotor_koopman_datafree-1.0.dist-info/RECORD
